fumus/__init__.py
fumus/decorators/__init__.py
fumus/decorators/handler.py
fumus/decorators/mapper.py
fumus/decorators/wrapper.py
fumus/exceptions/__init__.py
fumus/exceptions/exception.py
fumus/queries/__init__.py
fumus/queries/itertools_mixin.py
fumus/queries/query.py
fumus/queries/query_generator.py
fumus/utils/__init__.py
fumus/utils/dict_item.py
fumus/utils/optional.py
fumus/utils/result.py
fumus-1.1.2.dist-info/LICENSE
fumus-1.1.2.dist-info/METADATA
fumus-1.1.2.dist-info/WHEEL
fumus-1.1.2.dist-info/RECORD
