Metadata-Version: 2.3
Name: fumus
Version: 1.1.2
Summary: Functional musings
Home-page: https://github.com/kaliv0/fumus
Keywords: query,functional,processing,collections,fluent API,queries
Author: kaliv0
Author-email: kaloyan.ivanov88@gmail.com
Requires-Python: >=3.12,<4.0
Classifier: Programming Language :: Python :: 3
Classifier: Programming Language :: Python :: 3.12
Classifier: Programming Language :: Python :: 3.13
Project-URL: Documentation, https://fumus.readthedocs.io/en/latest
Project-URL: Repository, https://github.com/kaliv0/fumus
